odoo8_addon_sale_stock_auto_move-8.0.1.0.0-py2.7-nspkg.pth
odoo_addons/sale_stock_auto_move/__openerp__.py
odoo_addons/sale_stock_auto_move/__init__.py
odoo_addons/sale_stock_auto_move/README.rst
odoo_addons/sale_stock_auto_move/data/sale_workflow.xml
odoo8_addon_sale_stock_auto_move-8.0.1.0.0.dist-info/top_level.txt
odoo8_addon_sale_stock_auto_move-8.0.1.0.0.dist-info/WHEEL
odoo8_addon_sale_stock_auto_move-8.0.1.0.0.dist-info/RECORD
odoo8_addon_sale_stock_auto_move-8.0.1.0.0.dist-info/metadata.json
odoo8_addon_sale_stock_auto_move-8.0.1.0.0.dist-info/DESCRIPTION.rst
odoo8_addon_sale_stock_auto_move-8.0.1.0.0.dist-info/METADATA
odoo8_addon_sale_stock_auto_move-8.0.1.0.0.dist-info/namespace_packages.txt
