Metadata-Version: 2.0
Name: odoo8-addon-sale-stock-auto-move
Version: 8.0.1.0.0
Summary: Automatic Move Processing For Sale Delivery
Home-page: http://acsone.eu
Author: UNKNOWN
Author-email: UNKNOWN
License: AGPL-3
Platform: UNKNOWN
Requires-Dist: odoo (<9.0a,>=8.0a)
Requires-Dist: odoo8-addon-stock-auto-move
Classifier: Programming Language :: Python :: 2.7
Classifier: Framework :: Odoo
Classifier: License :: OSI Approved :: GNU Affero General Public License v3
